dynetx/__init__.py
dynetx/algorithms/__init__.py
dynetx/algorithms/assortativity.py
dynetx/algorithms/paths.py
dynetx/classes/__init__.py
dynetx/classes/dyndigraph.py
dynetx/classes/dyngraph.py
dynetx/classes/function.py
dynetx/readwrite/__init__.py
dynetx/readwrite/edgelist.py
dynetx/readwrite/json_graph/__init__.py
dynetx/readwrite/json_graph/node_link.py
dynetx/utils/__init__.py
dynetx/utils/decorators.py
dynetx/utils/misc.py
dynetx/utils/transform.py
dynetx-0.3.1.dist-info/LICENSE
dynetx-0.3.1.dist-info/METADATA
dynetx-0.3.1.dist-info/WHEEL
dynetx-0.3.1.dist-info/top_level.txt
dynetx-0.3.1.dist-info/RECORD
