Metadata-Version: 2.1
Name: dynetx
Version: 0.3.1
Summary: Dynamic Network library
Home-page: https://github.com/GiulioRossetti/dynetx
Author: Giulio Rossetti
Author-email: giulio.rossetti@gmail.com
License: BSD-Clause-2
Keywords: dynamic-networks
Platform: UNKNOWN
Classifier: Development Status :: 4 - Beta 
Classifier: Intended Audience :: Developers
Classifier: Topic :: Software Development :: Build Tools
Classifier: License :: OSI Approved :: GNU General Public License v3 or later (GPLv3+)
Classifier: Operating System :: OS Independent
Classifier: Programming Language :: Python
Classifier: Programming Language :: Python :: 3
License-File: LICENSE
